familycli/__init__.py
familycli/main.py
familycli/auth/__init__.py
familycli/auth/encryption.py
familycli/auth/user_manager.py
familycli/chat/__init__.py
familycli/chat/chat_engine.py
familycli/chat/llm_conversation_director.py
familycli/chat/response_generator.py
familycli/chat/session_manager.py
familycli/chat/streaming_handler.py
familycli/config/__init__.py
familycli/config/config_manager.py
familycli/config/db_manager.json
familycli/config/default_personas.json
familycli/config/llm_providers.json
familycli/config/user_config_manager.py
familycli/database/__init__.py
familycli/database/backup_utils.py
familycli/database/db_manager.py
familycli/database/migration_v1_1.py
familycli/database/models.py
familycli/llm/__init__.py
familycli/llm/api_handler.py
familycli/llm/model_validator.py
familycli/llm/streaming_client.py
familycli/llm/universal_llm_manager.py
familycli/llm/providers/__init__.py
familycli/llm/providers/anthropic_provider.py
familycli/llm/providers/base_provider.py
familycli/llm/providers/cerebras_provider.py
familycli/llm/providers/google_provider.py
familycli/llm/providers/groq_provider.py
familycli/llm/providers/openai_provider.py
familycli/personas/__init__.py
familycli/personas/family_tree_manager.py
familycli/personas/feedback_manager.py
familycli/personas/learning_engine.py
familycli/personas/memory_manager.py
familycli/personas/persona_manager.py
familycli/personas/persona_pack_manager.py
familycli/personas/relationship_manager.py
familycli/personas/scene_manager.py
familycli/ui/__init__.py
familycli/ui/cli_interface.py
familycli/ui/markdown_renderer.py
familycli/ui/rich_components.py
familycli/ui/streaming_ui.py
familycli-1.1.0.dist-info/licenses/LICENCE
familycli-1.1.0.dist-info/METADATA
familycli-1.1.0.dist-info/WHEEL
familycli-1.1.0.dist-info/entry_points.txt
familycli-1.1.0.dist-info/top_level.txt
familycli-1.1.0.dist-info/RECORD
