Metadata-Version: 2.4
Name: familycli
Version: 1.1.0
Summary: A warm, child-safe AI family chat experience in your terminal
Author-email: AIMLDev726 <aistudentlearn4@gmail.com>
License: Mozilla Public License Version 2.0
Project-URL: homepage, https://github.com/AIMLDev726/ai-family-cli
Project-URL: repository, https://github.com/AIMLDev726/ai-family-cli
Project-URL: documentation, https://github.com/AIMLDev726/ai-family-cli/blob/main/README.md
Project-URL: issues, https://github.com/AIMLDev726/ai-family-cli/issues
Project-URL: changelog, https://github.com/AIMLDev726/ai-family-cli/blob/main/CHANGELOG.md
Keywords: ai,family,chat,cli,children,safe,conversation
Classifier: Development Status :: 4 - Beta
Classifier: Intended Audience :: End Users/Desktop
Classifier: Intended Audience :: Education
Classifier: Programming Language :: Python :: 3
Classifier: Programming Language :: Python :: 3.10
Classifier: Programming Language :: Python :: 3.11
Classifier: Programming Language :: Python :: 3.12
Classifier: Programming Language :: Python :: 3.13
Classifier: Topic :: Communications :: Chat
Classifier: Topic :: Education
Classifier: Topic :: Scientific/Engineering :: Artificial Intelligence
Classifier: Environment :: Console
Classifier: Operating System :: OS Independent
Classifier: License :: OSI Approved :: Mozilla Public License 2.0 (MPL 2.0)
Classifier: Natural Language :: English
Requires-Python: >=3.10
License-File: LICENCE
Requires-Dist: rich>=13.7.0
Requires-Dist: typer>=0.9.0
Requires-Dist: prompt_toolkit>=3.0.43
Requires-Dist: colorama>=0.4.6
Requires-Dist: click>=8.1.3
Requires-Dist: tabulate>=0.9.0
Requires-Dist: sqlalchemy>=2.0.0
Requires-Dist: aiosqlite>=0.20.0
Requires-Dist: cryptography>=42.0.0
Requires-Dist: bcrypt>=4.1.2
Requires-Dist: aiohttp>=3.9.0
Requires-Dist: httpx>=0.27.0
Requires-Dist: requests>=2.32.3
Requires-Dist: async-timeout>=4.0.3
Requires-Dist: aioconsole>=0.6.2
Requires-Dist: openai>=1.30.0
Requires-Dist: anthropic>=0.30.0
Requires-Dist: google-generativeai>=0.7.0
Requires-Dist: python-dotenv>=1.0.1
Requires-Dist: markdown-it-py>=3.0.0
Requires-Dist: python-dateutil>=2.9.0
Requires-Dist: jsonschema>=4.22.0
Requires-Dist: pyyaml>=6.0.1
Requires-Dist: tenacity>=8.3.0
Requires-Dist: packaging>=24.0
Dynamic: license-file
